Metadata-Version: 1.1
Name: py420chan
Version: 0.0.3
Summary: Python 420chan API Wrapper. Based on the BASC-py4chan 4chan API Wrapper.
Home-page: http://github.com/bibanon/py420chan
Author: Antonizoon Overtwater
Author-email: antonizoon@bibanon.org
License:             DO WHAT THE FUCK YOU WANT TO PUBLIC LICENSE
